{
   "created_on": "2020-05-01 10:14:15.656 ",

   "shipping": {
     "customer": "Peter P Peterson",
     "address": "Longroad 1343",
     "city": "Peterburg",
     "region": "",
     "state": "PE",
     "country": "Peteonia",
     "delivery_notes": "Leave at the gate"
    },

     "tracking": {
       "company": "ups",
       "tracking_number": "22122X211SD",
       "status": "ontruck",
       "estimated_delivery":"2020-05-01 10:14:15.656 "
     },
   

   "payment": {
     "method": "visa",
     "transaction_id": "2312213312XXXTD"
   },

   "products": 
     {"id": 2,"name":"Hand Cenitizer","unit_cost":1000, "currency":"USDA"}
   
 }


 {
  "created_on": "2020-05-01 10:14:15.656 ",

  "shipping": {
    "customer": "Carollo Pete",
    "address": "Booxwood Cricle 1343",
    "city": "Maplewood",
    "state": "NJ",
    "country": "US",
    "delivery_notes": "Leave at the gate"
  },

    "tracking": {
      "company": "ups",
      "tracking_number": "12584882X211SD",
      "status": "Pending Shipping",
      "estimated_delivery":"2020-05-01 10:14:15.656 "
    },
  

  "payment": {
    "method": "visa",
    "transaction_id": "2312213312XXXTD"
  },

  "products": {
    "name":"Sterilite Container","unit_cost":70.00, "currency":"USDA"
  }
}



{
  "created_on": "2020-05-18 10:14:15.656 ",

  "shipping": {
    "customer": "Sam Rita",
    "address": "147 Correja Ave",
    "city": "Edison",
    "state": "NJ",
    "country": "US",
    "delivery_notes": "Leave at the gate"
  },

    "tracking": {
      "company": "ups",
      "tracking_number": "1ZRX11320344044707",
      "status": "Out for the delivery",
      "estimated_delivery":"2020-05-20 10:14:15.656 "
    },
  

  "payment": {
    "method": "visa",
    "transaction_id": "2312213312XXXTD"
  },

  "products": {
    "name": "Facial Tissue","unit_cost":25.00, "currency":"USDA"
  }
}



{
  "created_on": "2020-05-09 10:14:15.656 ",

  "shipping": {
    "customer": "Mandy madonic",
    "address": "343 Half Acre Rd",
    "city": "Englewood",
    "state": "WV",
    "country": "US",
    "delivery_notes": "Leave at the Door"
  },

    "tracking": {
      "company": "ups",
      "tracking_number": "22122X211SD",
      "status": "Delivered",
      "estimated_delivery":"2020-05-12 10:14:15.656 "
    },
  

  "payment": {
    "method": "visa",
    "transaction_id": "2312213312XXXTD"
  },

  "products": 
    {"name": "Hand Warmers","unit_cost":37.00, "currency":"USDA"}
  
}